napari_laptrack/__init__.py
napari_laptrack/_function.py
napari_laptrack/_tests/__init__.py
napari_laptrack/_tests/test_function.py
napari_laptrack-0.2.0.dist-info/LICENSE
napari_laptrack-0.2.0.dist-info/METADATA
napari_laptrack-0.2.0.dist-info/WHEEL
napari_laptrack-0.2.0.dist-info/entry_points.txt
napari_laptrack-0.2.0.dist-info/top_level.txt
napari_laptrack-0.2.0.dist-info/RECORD
