Metadata-Version: 2.1
Name: napari-laptrack
Version: 0.2.0
Summary: Tracking particles in Napari, based on the LapTrack library
Home-page: https://github.com/haesleinhuepf/napari_laptrack
Author: Robert Haase
Author-email: robert.haase@tu-dresden.de
License: BSD-3
Classifier: Development Status :: 2 - Pre-Alpha
Classifier: Intended Audience :: Science/Research
Classifier: Framework :: napari
Classifier: Topic :: Scientific/Engineering :: Image Processing
Classifier: Programming Language :: Python
Classifier: Programming Language :: Python :: 3
Classifier: Programming Language :: Python :: 3.8
Classifier: Programming Language :: Python :: 3.9
Classifier: Operating System :: OS Independent
Classifier: License :: OSI Approved :: BSD License
Requires-Python: >=3.6
License-File: LICENSE
Requires-Dist: napari-plugin-engine (>=0.1.4)
Requires-Dist: numpy
Requires-Dist: napari-tools-menu
Requires-Dist: napari-time-slicer
Requires-Dist: laptrack (>=0.10.0)
Requires-Dist: napari-skimage-regionprops (>=0.9.0)
Requires-Dist: pandas
